wcartist/__init__.py
wcartist/artist.py
wcartist/color.py
wcartist-0.0.2.data/scripts/wcartist
wcartist-0.0.2.dist-info/METADATA
wcartist-0.0.2.dist-info/WHEEL
wcartist-0.0.2.dist-info/top_level.txt
wcartist-0.0.2.dist-info/RECORD
