Metadata-Version: 2.1
Name: wcartist
Version: 0.0.2
Summary: wcartist is a module to create a word cloud image.
Home-page: https://github.com/koji/wcartist
Author: koji kanao
Author-email: koji.kanao@nyu.edu
License: MIT
Platform: UNKNOWN
Requires-Dist: docopt
Requires-Dist: Pillow
Requires-Dist: wordcloud
Requires-Dist: numpy
Requires-Dist: matplotlib
